{
  "155A Venice": 138,
  "3d-wax-printer": 148,
  "AC2_UPS_snl": 239,
  "Admin: Add External Member": 240,
  "Admin: Annual External Membership Service": 241,
  "Admin: Billing Adjustment": 242,
  "Admin: ID Card Key": 243,
  "Admin: Job or Company Ad": 244,
  "Admin: New External Account": 245,
  "Admin: Parking Sponsorship": 246,
  "afm2": 116,
  "AFM: Asylum Cypher ES": 459,
  "afm-asylum-loaner": 129,
  "AFM: Bruker Icon": 392,
  "AFM-IR: Bruker IconIR": 393,
  "AFM NanoCue": 227,
  "afm-nsil": 176,
  "AFM: Park FX-40": 396,
  "AFM: Park NX-10": 397,
  "AIX200": 4,
  "AIXCCS": 5,
  "AIXCCS bake": 229,
  "AIXCCS bakeout": 249,
  "aixtron-graphene": 186,
  "aja2-evap": 113,
  "aja-evap": 175,
  "aja-sputter": 1,
  "All Litho Training": 193,
  "alphastep": 126,
  "alphastep2": 167,
  "alveole": 174,
  "American Ultraviolet Cool Cure Chamber": 471,
  "AML Bonder": 230,
  "asml": 38,
  "asylum-mfp3d-afm": 134,
  "Auger_snl": 252,
  "aw610_l": 14,
  "aw610_r": 15,
  "B1T1 Flexible Oxide Anneal": 194,
  "B1T2 Flexible Oxide": 206,
  "B1T3 Flexible Poly": 210,
  "B1T4 Flexible LTO": 211,
  "B2T5 Clean Anneal": 207,
  "B2T6 Clean Oxide": 208,
  "B2T7 Flexible Nitride": 212,
  "B2T8 Clean LTO": 213,
  "B3T10 Clean Nitride": 214,
  "B3T11 Clean TEOS": 215,
  "B3T12 Clean Poly": 216,
  "B3T9 Clean Oxide": 209,
  "Bambu Lab H2D": 470,
  "Bambu Lab P1S": 236,
  "Beckman centrifuge": 223,
  "biologic": 151,
  "bluem": 46,
  "Bruker C-AFM Module and Probe Holder": 257,
  "Bruker CMP": 228,
  "Bruker TR-TUNA Probe Holder": 258,
  "Buehler AutoMet Polisher": 405,
  "Buehler IsoMet Saw": 406,
  "ccp-dep": 27,
  "centrifuge": 130,
  "cha-evap": 219,
  "ck-test": 7,
  "ck-test2": 101,
  "cmp": 159,
  "Contact Angle Goniometer: Rame-Hart 290": 259,
  "cpd": 70,
  "Cressington Sputter Coater": 260,
  "cvd-nanotube": 119,
  "cytoviva": 179,
  "DB235 FIB_snl": 262,
  "Dektak Stylus Profiler": 263,
  "Demo Tool": 12,
  "DENSsolutions Climate 3+ Gas Cell Holder": 407,
  "DENSsolutions Lightening Arctic Holder": 467,
  "DENSsolutions Lightening Arctic MEMS Holder": 463,
  "DENSsolutions Wildfire MEMS Holder": 408,
  "Diener Nano Plasma Asher": 472,
  "disco-backgrind": 182,
  "DISCO wafersaw": 144,
  "disperser": 160,
  "DMA: TA Instrument Q800": 265,
  "DSC_Q2000_smf": 266,
  "Dynamic Light Scattering(DLS)_smf": 267,
  "EBL: BEAMER License 1": 268,
  "EBL: BEAMER License 2": 269,
  "EBL: EBPG 1": 271,
  "EBL: EBPG 2": 272,
  "EBL: TRACER License": 274,
  "eddycurrent": 145,
  "edwards-sputter-evap": 220,
  "epi2": 13,
  "evalign": 39,
  "evalign2": 40,
  "evbond": 94,
  "evgspraycoat": 37,
  "FCR Lab Safety Tour": 481,
  "FEI Tecnai F20": 280,
  "FEI Titan G2 ETEM": 281,
  "FEI Titan K3 Computer": 282,
  "FIB: FEI Helios": 277,
  "FIB Helios EDS": 283,
  "fiji1": 9,
  "fiji2": 50,
  "fiji3": 51,
  "filmetrics": 96,
  "filmetrics2": 218,
  "Filmetrics 4PP": 493,
  "Film Thickness: Filmetrics F40": 284,
  "Fischione 2021 Analytical Tomography Holder": 409,
  "Fischione 2040 Dual Axis Tomography Holder": 410,
  "flipchipbonder": 158,
  "form2-3d-printer": 11,
  "fumehood1": 140,
  "fumehood2": 139,
  "fumehood3": 137,
  "fumehood4": 136,
  "gasonics": 55,
  "Gas sorption: Quantachrome Autosorb iQ3": 288,
  "Gatan 628 Furnace Holder (Old)": 411,
  "Gatan 636 Cryo-cooling Holder": 412,
  "Gatan 652 Furnace Holder (New)": 413,
  "Gatan 677 Multispecimen Holder 2": 464,
  "Gatan Dimpler": 414,
  "Gatan Elsa Cryo-transfer Holder": 415,
  "Gatan Multispecimen Holder 1": 465,
  "Gatan PIPS": 426,
  "Gatan Pumping Station B": 466,
  "glovebox-l": 184,
  "glovebox-r": 183,
  "GPC: Tosho High-temperature EcoSEC": 289,
  "GPC: Tosho Room-temperature EcoSEC": 290,
  "gs-test": 221,
  "hdpcvd": 28,
  "headway2": 30,
  "headway3": 127,
  "heat-seal-press": 168,
  "heidelberg": 157,
  "heidelberg2": 124,
  "heidelberg3": 123,
  "Hiden-RGA": 235,
  "Hitachi TM4000 SEM": 378,
  "Horiba Raman Software Computer": 292,
  "hotplate-1": 165,
  "HT-TGA_DSC": 294,
  "hummer": 152,
  "Hummingbird Scientific Liquid Cell Holder": 418,
  "IBL: Velion": 295,
  "InSight Chips MEMS Liquid Cell Holder": 462,
  "Instron_smf": 297,
  "intlvac_evap": 54,
  "Intlvac IBE": 488,
  "Inverted Microscope": 419,
  "Ion Mill": 298,
  "jasco-uv-vis-nir": 155,
  "karlsuss": 41,
  "karlsuss2": 42,
  "keyence": 135,
  "Keyence VHX-X1 (Torramics)": 232,
  "Keyence VK Laser Scanning Microscope": 301,
  "Keyence VK-X3000 (Torramics)": 233,
  "KJL-evaporator": 302,
  "KJL-evaporator 2": 303,
  "KLA Tencor Profiler": 304,
  "ksbonder": 95,
  "lakeshore-hall": 149,
  "lampoly": 56,
  "lasercutter": 133,
  "laserscribe": 141,
  "laurell_dev-etch": 163,
  "laurell-G": 31,
  "laurell-R": 32,
  "LB Trough_smf": 306,
  "Leica Enuity Cryo Chamber": 420,
  "Leica Enuity Ultramicrotome": 421,
  "Leica TXP": 422,
  "lesker2-sputter": 171,
  "lesker-sputter": 146,
  "Leybold Univex Sputter": 307,
  "Linkam Temperature Stage": 308,
  "lithosolv": 71,
  "LPKF ProtoLaser U4": 231,
  "LUXOR Sputter Coater": 423,
  "MALS: Wyatt Dawn Heleos": 309,
  "malvern-dls": 153,
  "masksrub": 43,
  "matrix": 57,
  "Mechanical Polisher": 424,
  "micromanipulator6000": 181,
  "micromill": 187,
  "micromist-coater": 115,
  "MicroWriter ML3 (365 nm)": 473,
  "MicroWriter ML3 (385 nm)": 316,
  "mrc": 58,
  "mvd": 52,
  "nanoinkjet": 164,
  "nanoscribe": 10,
  "NanoSIMS": 333,
  "nanospec2": 97,
  "nanospec3": 156,
  "Nikon UDM": 425,
  "NPC Lab Safety Tour": 482,
  "Oak Data Access": 486,
  "Open Cure 365 nm LED System": 478,
  "optomec": 120,
  "optomec-printer": 125,
  "oriel-duv": 154,
  "Ox-35": 64,
  "Ox-ALE": 224,
  "oxford-rie": 59,
  "Ox-gen": 189,
  "Ox-Ox": 225,
  "Ox-PECVD": 226,
  "p2": 99,
  "p5000etch": 60,
  "parcoater": 128,
  "Particle Analysis: NovaTouch": 347,
  "PFIB: TFS Hydra": 348,
  "Phenom Pharos FEG-SEM": 382,
  "PHI_XPS_snl": 349,
  "plasma-etch": 114,
  "Plasma Prep Cleaner_smf": 350,
  "Polarized LM: Nikon LV100": 351,
  "Porosimeter": 352,
  "Probe Station P200L": 222,
  "Profilometer_smf": 353,
  "prometrix": 98,
  "Protochips Aduro 500 MEMS Heating-Biasing Holder": 427,
  "Protochips Faraday Cup Holder": 428,
  "Prusa MK3": 238,
  "PT-DSE": 67,
  "PT-MTL": 66,
  "PT-Ox": 65,
  "pv-tester": 122,
  "raith": 150,
  "Raman: Horiba XploRA+": 293,
  "Raman-TERS: Horiba LabRAM": 394,
  "Raman: WITec alpha300 Apyron": 483,
  "redfurnace": 162,
  "Resist Oven Bottom": 457,
  "Resist Oven Top": 458,
  "Rheometer-DMA": 361,
  "Rheometer: TA Instrument ARES-G2": 362,
  "Rheosense": 363,
  "RIE: Oxford PlasmaPro 80": 364,
  "samco": 68,
  "Samco Ozone Cleaner": 375,
  "savannah": 8,
  "SAXS: SAXSpoint 700": 484,
  "Scanning Kelvin Probe: SKP505": 376,
  "seki-diamond": 29,
  "SEM and FIB: Data Processing PC": 479,
  "SEM: FEI Magellan": 278,
  "SEM: GenISys InSPEC": 377,
  "sem-merlin": 169,
  "SEM Mill: Fischione 1061": 379,
  "SEM Mill: Vacuum Transfer Vessel": 381,
  "SEM Mill: VTV Cross Section Station": 380,
  "SEM: ProSEM License": 383,
  "SEM: TFS Apreo": 384,
  "SEM: Zeiss Gemini 560": 385,
  "Signatone 4PP": 234,
  "sinton-lifetime-tester": 142,
  "Sirion SEM_snl": 386,
  "SMF Safety Orientation": 480,
  "s-neox": 172,
  "SNF Safety Tour": 191,
  "sonicator": 180,
  "Spectroscopy: Agilent Cary 6000i UV-Vis-NIR": 387,
  "Spectroscopy: Horiba FluoroLog Fluorimeter": 388,
  "Spectroscopy: Nicolet iS50 FT-IR Spectrometer": 390,
  "Spilker 004 Office Computer": 391,
  "spincoat-g3p8": 173,
  "SSI_XPS_snl": 402,
  "Staff SMF Orientation": 403,
  "stresstest": 100,
  "Struers TenuPol-5": 431,
  "stsetch": 61,
  "svgcoat": 33,
  "svgcoat2": 34,
  "svgcoat3": 35,
  "svgcoat4": 36,
  "svgdev": 44,
  "svgdev2": 45,
  "technics": 69,
  "TEM: DensSolutions MEMS Heating Holder": 468,
  "TEM: Gatan Pumping Station B - Bottom": 416,
  "TEM: Gatan Pumping Station B - Top": 417,
  "TEM: InSight Liquid Cell Holder Deep Lab": 469,
  "TEM: Titan Pumping Station - Bottom": 433,
  "TEM: Titan Pumping Station - Top": 434,
  "TFS Spectra 300": 432,
  "TFS Talos F200i": 461,
  "TFS Talos L120C": 460,
  "TGA: TA Instrument Q500": 437,
  "thermco3": 17,
  "thermco4": 18,
  "thermcolto": 24,
  "thermcopoly2": 25,
  "thermolyne": 143,
  "thermoscientific-oven": 185,
  "thinky-mixer": 170,
  "trainee": 166,
  "tylan9": 19,
  "tylanfga": 20,
  "uetch": 62,
  "uvcure": 47,
  "voltera": 118,
  "VST Hi-Vac Oven": 440,
  "wbclean-1": 72,
  "wbclean-2": 73,
  "wbclean-3": 74,
  "wbclean_res-HF": 76,
  "wbclean_res-hotphos": 77,
  "wbclean_res-piranha": 75,
  "wbdecon": 78,
  "wbexfab_dev": 132,
  "wbexfab_dev-plug": 188,
  "wbexfab_solv": 178,
  "wbexfab_solv-plug": 177,
  "wbflexcorr-1": 79,
  "wbflexcorr-2": 80,
  "wbflexcorr-3": 81,
  "wbflexcorr-4": 82,
  "wbflexcorr-plug": 86,
  "wbflexcorr-plug2": 87,
  "wbflexsolv": 83,
  "wbflexsolv-1": 84,
  "wbflexsolv-2": 85,
  "wbflexsolv-plug": 88,
  "wbgen2-hp": 192,
  "wbmiscres": 89,
  "wbresstrip-1": 90,
  "wbresstrip-2": 91,
  "wbresstrip-3": 92,
  "wbresstrip-4": 93,
  "Wet Bench: Acids 1 (FCR)": 474,
  "Wet Bench: Acids 2 (FCR)": 475,
  "Wet Bench: Acids (NPC)": 441,
  "Wet Bench: Bases 1 (FCR)": 476,
  "Wet Bench: Bases 2 (FCR)": 477,
  "Wet Bench: Bases (NPC)": 442,
  "Wet Bench: Solvents (FCR)": 491,
  "Wet Bench: Solvents (NPC)": 489,
  "Wet Bench: Spinner (FCR)": 492,
  "Wet Bench: Spinner (NPC)": 490,
  "white-oven": 48,
  "Wire Bonder": 444,
  "WLI: Zygo NexView 9000": 487,
  "woollam": 161,
  "xactix": 63,
  "XCT: 620 Versa XRM": 446,
  "XCT: Image Analysis Workstation": 445,
  "XPS: PHI Transfer Vessel": 451,
  "XPS: PHI Transfer Vessel (2 Inch)": 452,
  "XPS: PHI VersaProbe 3": 453,
  "XPS: PHI VersaProbe 4": 454,
  "XRD: D8 Venture": 261,
  "XRD: Empyrean 1": 455,
  "XRD: Empyrean 2": 456,
  "XRD: Laue": 305,
  "XRD: X'Pert MRD": 450,
  "XRD: XRDynamic 500": 485,
  "yes": 49,
  "yes2": 121,
  "zygo": 117
}